xff/__init__.py
xff/_version.py
xff/middleware.py
django_xff-1.4.0.dist-info/LICENSE
django_xff-1.4.0.dist-info/METADATA
django_xff-1.4.0.dist-info/WHEEL
django_xff-1.4.0.dist-info/top_level.txt
django_xff-1.4.0.dist-info/RECORD
