Metadata-Version: 2.1
Name: django-xff
Version: 1.4.0
Summary: Django X-Forwarded-For Properly
Home-page: https://github.com/ferrix/xff/
Author: Ferrix Hovi
Author-email: ferrix@codetry.fi
License: MIT License
Classifier: Environment :: Web Environment
Classifier: Framework :: Django
Classifier: Framework :: Django :: 1.8
Classifier: Intended Audience :: Developers
Classifier: Operating System :: OS Independent
Classifier: Programming Language :: Python
Classifier: License :: OSI Approved :: MIT License
Classifier: Topic :: Internet :: WWW/HTTP
Classifier: Topic :: Internet :: WWW/HTTP :: Dynamic Content
License-File: LICENSE
